{
  "id": "a37c8ff4-f317-4083-8f29-484f2a88110e",
  "timestamp": "2025-11-21T03:44:04.933Z",
  "description": "Test checkpoint",
  "files": [
    {
      "path": "/test/file-1763696644933.ts",
      "content": "test content",
      "hash": "6ae8a75555209fd6c44157c0aed8016e763ff435a19cf186f76863140143ff72",
      "size": 12
    }
  ],
  "conversationState": [
    {
      "type": "user",
      "content": "Message 40",
      "timestamp": "2025-11-21T03:44:04.933Z"
    },
    {
      "type": "user",
      "content": "Message 41",
      "timestamp": "2025-11-21T03:44:04.933Z"
    },
    {
      "type": "user",
      "content": "Message 42",
      "timestamp": "2025-11-21T03:44:04.933Z"
    },
    {
      "type": "user",
      "content": "Message 43",
      "timestamp": "2025-11-21T03:44:04.933Z"
    },
    {
      "type": "user",
      "content": "Message 44",
      "timestamp": "2025-11-21T03:44:04.933Z"
    },
    {
      "type": "user",
      "content": "Message 45",
      "timestamp": "2025-11-21T03:44:04.933Z"
    },
    {
      "type": "user",
      "content": "Message 46",
      "timestamp": "2025-11-21T03:44:04.933Z"
    },
    {
      "type": "user",
      "content": "Message 47",
      "timestamp": "2025-11-21T03:44:04.933Z"
    },
    {
      "type": "user",
      "content": "Message 48",
      "timestamp": "2025-11-21T03:44:04.933Z"
    },
    {
      "type": "user",
      "content": "Message 49",
      "timestamp": "2025-11-21T03:44:04.933Z"
    }
  ],
  "metadata": {
    "model": "glm-4.6",
    "triggeredBy": "test"
  }
}